FiberFusing/__init__.py
FiberFusing/_version.py
FiberFusing/background.py
FiberFusing/base_fused.py
FiberFusing/buffer.py
FiberFusing/connection.py
FiberFusing/connection_optimization.py
FiberFusing/coordinate_system.py
FiberFusing/directories.py
FiberFusing/fiber_structure.py
FiberFusing/geometry.py
FiberFusing/helper.py
FiberFusing/optical_structure.py
FiberFusing/plottings.py
FiberFusing/utils.py
FiberFusing/components/__init__.py
FiberFusing/components/base_class.py
FiberFusing/components/linestring.py
FiberFusing/components/point.py
FiberFusing/components/polygon.py
FiberFusing/components/utils.py
FiberFusing/configuration/__init__.py
FiberFusing/configuration/line/__init__.py
FiberFusing/configuration/line/configuration_01x01.py
FiberFusing/configuration/line/configuration_02x02.py
FiberFusing/configuration/line/configuration_03x03.py
FiberFusing/configuration/line/configuration_04x04.py
FiberFusing/configuration/line/configuration_05x05.py
FiberFusing/configuration/ring/__init__.py
FiberFusing/configuration/ring/configuration_01x01.py
FiberFusing/configuration/ring/configuration_02x02.py
FiberFusing/configuration/ring/configuration_03x03.py
FiberFusing/configuration/ring/configuration_04x04.py
FiberFusing/configuration/ring/configuration_05x05.py
FiberFusing/configuration/ring/configuration_06x06.py
FiberFusing/configuration/ring/configuration_07x07.py
FiberFusing/configuration/ring/configuration_10x10.py
FiberFusing/configuration/ring/configuration_12x12.py
FiberFusing/configuration/ring/configuration_19x19.py
FiberFusing/configuration/ring/mode_groupe_pl_6.py
FiberFusing/configuration/ring/scaling_photonic_lantern_10.py
FiberFusing/fiber/__init__.py
FiberFusing/fiber/catalogue.py
FiberFusing/fiber/generic_fiber.py
FiberFusing/fiber/loader.py
FiberFusing/fiber/structure_collection.py
FiberFusing/fiber/fiber_files/1550BHP.yaml
FiberFusing/fiber/fiber_files/DCF13.yaml
FiberFusing/fiber/fiber_files/DCF1300S_20.yaml
FiberFusing-1.9.10.post0.dist-info/LICENSE
FiberFusing-1.9.10.post0.dist-info/METADATA
FiberFusing-1.9.10.post0.dist-info/WHEEL
FiberFusing-1.9.10.post0.dist-info/top_level.txt
FiberFusing-1.9.10.post0.dist-info/RECORD
