Metadata-Version: 2.1
Name: FiberFusing
Version: 1.9.10.post0
Summary: A package fiber fusing configuration simulating the transverse fusion of fiber optics.
Author-email: Martin Poinsinet de Sivry-Houle <martin.poinsinet.de.sivry@gmail.com>
License: MIT License
Project-URL: Homepage, https://github.com/MartinPdeS/FiberFusing
Project-URL: Documentation, https://martinpdes.github.io/FiberFusing/
Project-URL: Repository, https://github.com/MartinPdeS/FiberFusing.git
Keywords: fiber,fusing
Classifier: Programming Language :: Python
Classifier: Programming Language :: Python :: 3
Classifier: Programming Language :: Python :: 3.11
Classifier: Programming Language :: Python :: 3.12
Classifier: Programming Language :: Python :: Implementation :: CPython
Classifier: Development Status :: 4 - Beta
Classifier: Topic :: Scientific/Engineering :: Physics
Classifier: License :: OSI Approved :: MIT License
Classifier: Intended Audience :: Science/Research
Requires-Python: >=3.10
License-File: LICENSE
Requires-Dist: pyyaml~=6.0
Requires-Dist: pydantic>=2.9
Requires-Dist: scipy~=1.11
Requires-Dist: numpy<3.0,>=1.26
Requires-Dist: shapely~=2.0
Requires-Dist: MPSPlots
Requires-Dist: PyOptik
Provides-Extra: documentation
Requires-Dist: numpydoc~=1.8; extra == "documentation"
Requires-Dist: sphinx>=6; extra == "documentation"
Requires-Dist: sphinx-gallery~=0.17; extra == "documentation"
Requires-Dist: sphinx-rtd-theme~=2.0; extra == "documentation"
Requires-Dist: pydata-sphinx-theme~=0.15; extra == "documentation"
Provides-Extra: testing
Requires-Dist: pytest<9.0,>=7.4; extra == "testing"
Requires-Dist: pytest-cov<6,>=2; extra == "testing"
Requires-Dist: pytest-json-report~=1.5; extra == "testing"
Requires-Dist: flake8==7.1.1; extra == "testing"
Requires-Dist: coverage~=7.6; extra == "testing"
